initt/__init__.py
initt/cmdline.py
initt/templates/mac/.gitignore.jinja
initt/templates/nodejs/.gitignore.jinja
initt/templates/nodejs/README.md.jinja
initt/templates/nodejs/extensions.json.jinja
initt/templates/nodejs/index.ts.jinja
initt/templates/nodejs/launch.json.jinja
initt/templates/nodejs/package.json.jinja
initt/templates/nodejs/settings.json.jinja
initt/templates/nodejs/tsconfig.json.jinja
initt/templates/python/.gitignore.jinja
initt/templates/python/README.md.jinja
initt/templates/python/__init__.py.jinja
initt/templates/python/cmdline.py.jinja
initt/templates/python/extensions.json.jinja
initt/templates/python/launch.json.jinja
initt/templates/python/pyproject.toml.jinja
initt/templates/python/requirements.txt.jinja
initt/templates/python/settings.json.jinja
initt-0.0.18.dist-info/METADATA
initt-0.0.18.dist-info/WHEEL
initt-0.0.18.dist-info/entry_points.txt
initt-0.0.18.dist-info/top_level.txt
initt-0.0.18.dist-info/RECORD
