Metadata-Version: 2.4
Name: initt
Version: 0.0.18
Summary: Project templates
Author-email: Seven <1162584980@qq.com>
Maintainer-email: Seven <1162584980@qq.com>
License: MIT License
Classifier: License :: OSI Approved :: MIT License
Classifier: Environment :: Console :: Curses
Classifier: Operating System :: OS Independent
Classifier: Programming Language :: Python :: 3
Classifier: Topic :: Utilities
Requires-Python: >=3.11
Requires-Dist: click
Requires-Dist: types-click
Requires-Dist: Jinja2
Requires-Dist: questionary
Provides-Extra: dev
Requires-Dist: build; extra == "dev"
Requires-Dist: twine; extra == "dev"
